twitterscraper/__init__.py
twitterscraper/main.py
twitterscraper/query.py
twitterscraper/ts_logger.py
twitterscraper/tweet.py
twitterscraper/user.py
sriram_twitter_scraper-1.3.2.dist-info/LICENSE
sriram_twitter_scraper-1.3.2.dist-info/METADATA
sriram_twitter_scraper-1.3.2.dist-info/WHEEL
sriram_twitter_scraper-1.3.2.dist-info/entry_points.txt
sriram_twitter_scraper-1.3.2.dist-info/top_level.txt
sriram_twitter_scraper-1.3.2.dist-info/RECORD
