Metadata-Version: 2.1
Name: sriram-twitter-scraper
Version: 1.3.2
Summary: Tool for scraping Tweets
Home-page: https://github.com/sriramkumar1996/twitterscraper
Author: ['Ahmet Taspinar', 'Lasse Schuirmann', 'Sriram Kumar']
Author-email: srirambsk1996@gmail.com
License: MIT
Platform: UNKNOWN
Requires-Dist: coala-utils (~=0.5.0)
Requires-Dist: bs4
Requires-Dist: lxml
Requires-Dist: requests
Requires-Dist: billiard
